aga/__init__.py
aga/checks.py
aga/cli/__init__.py
aga/cli/app.py
aga/cli/ui.py
aga/config.py
aga/core/__init__.py
aga/core/context.py
aga/core/parameter.py
aga/core/problem.py
aga/core/suite.py
aga/core/utils.py
aga/defaults.toml
aga/gradescope/__init__.py
aga/gradescope/into_zip.py
aga/gradescope/main.py
aga/gradescope/metadata.py
aga/gradescope/resources/__init__.py
aga/gradescope/resources/run_autograder
aga/gradescope/resources/setup-310.sh
aga/gradescope/resources/setup-311.sh
aga/gradescope/resources/setup.py
aga/gradescope/schema.py
aga/loader.py
aga/prize.py
aga/py.typed
aga/runner.py
aga/score.py
aga/util.py
aga-0.13.10.dist-info/LICENSE.md
aga-0.13.10.dist-info/METADATA
aga-0.13.10.dist-info/WHEEL
aga-0.13.10.dist-info/entry_points.txt
aga-0.13.10.dist-info/RECORD
