Metadata-Version: 2.1
Name: aga
Version: 0.13.10
Summary: aga grades assignments
Home-page: https://github.com/nihilistkitten/aga
License: MIT
Author: Riley Shahar
Author-email: riley.shahar@gmail.com
Requires-Python: >=3.10.0,<4.0.0
Classifier: License :: OSI Approved :: MIT License
Classifier: Programming Language :: Python :: 3
Classifier: Programming Language :: Python :: 3.10
Classifier: Programming Language :: Python :: 3.11
Requires-Dist: dacite (>=1.6.0,<2.0.0)
Requires-Dist: dataclasses-json (>=0.5.6,<0.6.0)
Requires-Dist: dill (>=0.3.4,<0.4.0)
Requires-Dist: gradescope-utils (>=0.5.0,<0.6.0)
Requires-Dist: toml (>=0.10.2,<0.11.0)
Requires-Dist: typer[all] (>=0.7.0,<0.8.0)
Requires-Dist: types-toml (>=0.10.8,<0.11.0)
Project-URL: Documentation, https://aga.readthedocs.io
Project-URL: Repository, https://github.com/nihilistkitten/aga
